{
  "code": 0,
  "model": [
    {
      "index": "A",
      "data": [
        {
          "countryName": "阿富汗",
          "countryEnName": "Afghanistan",
          "countryCode": "AFG"
        },
        {
          "countryName": "安哥拉",
          "countryEnName": "Angola",
          "countryCode": "AGO"
        },
        {
          "countryName": "安圭拉",
          "countryEnName": "Anguilla",
          "countryCode": "AIA"
        },
        {
          "countryName": "阿尔巴尼亚",
          "countryEnName": "Albania",
          "countryCode": "ALB"
        },
        {
          "countryName": "安道尔",
          "countryEnName": "Andorra",
          "countryCode": "AND"
        },
        {
          "countryName": "阿联酋",
          "countryEnName": "United Arab Emirates ",
          "countryCode": "ARE"
        },
        {
          "countryName": "阿根廷",
          "countryEnName": "Argentina",
          "countryCode": "ARG"
        },
        {
          "countryName": "亚美尼亚",
          "countryEnName": "Armenia",
          "countryCode": "ARM"
        },
        {
          "countryName": "澳大利亚",
          "countryEnName": "Australia",
          "countryCode": "AUS"
        },
        {
          "countryName": "奥地利",
          "countryEnName": "Austria",
          "countryCode": "AUT"
        },
        {
          "countryName": "阿塞拜疆",
          "countryEnName": "Azerbaijan",
          "countryCode": "AZE"
        },
        {
          "countryName": "比利时",
          "countryEnName": "Belgium",
          "countryCode": "BEL"
        },
        {
          "countryName": "孟加拉国",
          "countryEnName": "Bangladesh",
          "countryCode": "BGD"
        }
      ]
    },
    {
      "index": "B",
      "data": [
        {
          "countryName": "保加利亚",
          "countryEnName": "Bulgaria",
          "countryCode": "BGR"
        },
        {
          "countryName": "巴林",
          "countryEnName": "Bahrain",
          "countryCode": "BHR"
        },
        {
          "countryName": "巴哈马",
          "countryEnName": "Bahamas ",
          "countryCode": "BHS"
        },
        {
          "countryName": "波黑",
          "countryEnName": "Bosnia and Herzegovina",
          "countryCode": "BIH"
        },
        {
          "countryName": "白俄罗斯",
          "countryEnName": "Belarus",
          "countryCode": "BLR"
        },
        {
          "countryName": "玻利维亚",
          "countryEnName": "Bolivia",
          "countryCode": "BOL"
        },
        {
          "countryName": "巴西",
          "countryEnName": "Brazil",
          "countryCode": "BRA"
        },
        {
          "countryName": "文莱",
          "countryEnName": "Brunei Darussalam",
          "countryCode": "BRN"
        },
        {
          "countryName": "不丹",
          "countryEnName": "Bhutan",
          "countryCode": "BTN"
        }
      ]
    },
    {
      "index": "C",
      "data": [
        {
          "countryName": "中非",
          "countryEnName": "Central African Republic ",
          "countryCode": "CAF"
        },
        {
          "countryName": "加拿大",
          "countryEnName": "Canada",
          "countryCode": "CAN"
        },
        {
          "countryName": "瑞士",
          "countryEnName": "Switzerland",
          "countryCode": "CHE"
        },
        {
          "countryName": "智利",
          "countryEnName": "Chile",
          "countryCode": "CHL"
        },
        {
          "countryName": "中国",
          "countryEnName": "China",
          "countryCode": "CHN"
        },
        {
          "countryName": "科特迪瓦",
          "countryEnName": "Côte d'Ivoire",
          "countryCode": "CIV"
        },
        {
          "countryName": "喀麦隆",
          "countryEnName": "Cameroon",
          "countryCode": "CMR"
        },
        {
          "countryName": "刚果（金）",
          "countryEnName": "Congo (the Democratic Republic of the)",
          "countryCode": "COD"
        },
        {
          "countryName": "刚果（布）",
          "countryEnName": "Congo",
          "countryCode": "COG"
        },
        {
          "countryName": "哥伦比亚",
          "countryEnName": "Colombia",
          "countryCode": "COL"
        },
        {
          "countryName": "哥斯达黎加",
          "countryEnName": "Costa Rica",
          "countryCode": "CRI"
        },
        {
          "countryName": "古巴",
          "countryEnName": "Cuba",
          "countryCode": "CUB"
        },
        {
          "countryName": "塞浦路斯",
          "countryEnName": "Cyprus",
          "countryCode": "CYP"
        },
        {
          "countryName": "捷克",
          "countryEnName": "Czech Republic ",
          "countryCode": "CZE"
        }
      ]
    },
    {
      "index": "D",
      "data": [
        {
          "countryName": "德国",
          "countryEnName": "Germany",
          "countryCode": "DEU"
        },
        {
          "countryName": "吉布提",
          "countryEnName": "Djibouti",
          "countryCode": "DJI"
        },
        {
          "countryName": "多米尼克",
          "countryEnName": "Dominica",
          "countryCode": "DMA"
        },
        {
          "countryName": "丹麦",
          "countryEnName": "Denmark",
          "countryCode": "DNK"
        },
        {
          "countryName": "多米尼加",
          "countryEnName": "Dominican Republic ",
          "countryCode": "DOM"
        },
        {
          "countryName": "阿尔及利亚",
          "countryEnName": "Algeria",
          "countryCode": "DZA"
        }
      ]
    },
    {
      "index": "E",
      "data": [
        {
          "countryName": "厄瓜多尔",
          "countryEnName": "Ecuador",
          "countryCode": "ECU"
        },
        {
          "countryName": "埃及",
          "countryEnName": "Egypt",
          "countryCode": "EGY"
        },
        {
          "countryName": "西班牙",
          "countryEnName": "Spain",
          "countryCode": "ESP"
        },
        {
          "countryName": "爱沙尼亚",
          "countryEnName": "Estonia",
          "countryCode": "EST"
        },
        {
          "countryName": "埃塞俄比亚",
          "countryEnName": "Ethiopia",
          "countryCode": "ETH"
        }
      ]
    },
    {
      "index": "F",
      "data": [
        {
          "countryName": "芬兰",
          "countryEnName": "Finland",
          "countryCode": "FIN"
        },
        {
          "countryName": "斐济",
          "countryEnName": "Fiji",
          "countryCode": "FJI"
        },
        {
          "countryName": "法国",
          "countryEnName": "France",
          "countryCode": "FRA"
        }
      ]
    },
    {
      "index": "G",
      "data": [
        {
          "countryName": "英国",
          "countryEnName": "United Kingdom ",
          "countryCode": "GBR"
        },
        {
          "countryName": "格鲁吉亚",
          "countryEnName": "Georgia",
          "countryCode": "GEO"
        },
        {
          "countryName": "加纳",
          "countryEnName": "Ghana",
          "countryCode": "GHA"
        },
        {
          "countryName": "直布罗陀",
          "countryEnName": "Gibraltar",
          "countryCode": "GIB"
        },
        {
          "countryName": "几内亚",
          "countryEnName": "Guinea",
          "countryCode": "GIN"
        },
        {
          "countryName": "冈比亚",
          "countryEnName": "Gambia ",
          "countryCode": "GMB"
        },
        {
          "countryName": "几内亚比绍",
          "countryEnName": "Guinea-Bissau",
          "countryCode": "GNB"
        },
        {
          "countryName": "赤道几内亚",
          "countryEnName": "Equatorial Guinea",
          "countryCode": "GNQ"
        },
        {
          "countryName": "希腊",
          "countryEnName": "Greece",
          "countryCode": "GRC"
        },
        {
          "countryName": "格陵兰",
          "countryEnName": "Greenland",
          "countryCode": "GRL"
        },
        {
          "countryName": "危地马拉",
          "countryEnName": "Guatemala",
          "countryCode": "GTM"
        },
        {
          "countryName": "圭亚那",
          "countryEnName": "Guyana",
          "countryCode": "GUY"
        }
      ]
    },
    {
      "index": "H",
      "data": [
        {
          "countryName": "中国香港",
          "countryEnName": "Hong Kong SAR",
          "countryCode": "HKG"
        },
        {
          "countryName": "洪都拉斯",
          "countryEnName": "Honduras",
          "countryCode": "HND"
        },
        {
          "countryName": "克罗地亚",
          "countryEnName": "Croatia",
          "countryCode": "HRV"
        },
        {
          "countryName": "海地",
          "countryEnName": "Haiti",
          "countryCode": "HTI"
        },
        {
          "countryName": "匈牙利",
          "countryEnName": "Hungary",
          "countryCode": "HUN"
        }
      ]
    },
    {
      "index": "I",
      "data": [
        {
          "countryName": "印度尼西亚",
          "countryEnName": "Indonesia",
          "countryCode": "IDN"
        },
        {
          "countryName": "印度",
          "countryEnName": "India",
          "countryCode": "IND"
        },
        {
          "countryName": "爱尔兰",
          "countryEnName": "Ireland",
          "countryCode": "IRL"
        },
        {
          "countryName": "伊朗",
          "countryEnName": "Iran ",
          "countryCode": "IRN"
        },
        {
          "countryName": "伊拉克",
          "countryEnName": "Iraq",
          "countryCode": "IRQ"
        },
        {
          "countryName": "冰岛",
          "countryEnName": "Iceland",
          "countryCode": "ISL"
        },
        {
          "countryName": "以色列",
          "countryEnName": "Israel",
          "countryCode": "ISR"
        },
        {
          "countryName": "意大利",
          "countryEnName": "Italy",
          "countryCode": "ITA"
        }
      ]
    },
    {
      "index": "J",
      "data": [
        {
          "countryName": "牙买加",
          "countryEnName": "Jamaica",
          "countryCode": "JAM"
        },
        {
          "countryName": "约旦",
          "countryEnName": "Jordan",
          "countryCode": "JOR"
        },
        {
          "countryName": "日本",
          "countryEnName": "Japan",
          "countryCode": "JPN"
        }
      ]
    },
    {
      "index": "K",
      "data": [
        {
          "countryName": "哈萨克斯坦",
          "countryEnName": "Kazakhstan",
          "countryCode": "KAZ"
        },
        {
          "countryName": "肯尼亚",
          "countryEnName": "Kenya",
          "countryCode": "KEN"
        },
        {
          "countryName": "吉尔吉斯斯坦",
          "countryEnName": "Kyrgyzstan",
          "countryCode": "KGZ"
        },
        {
          "countryName": "柬埔寨",
          "countryEnName": "Cambodia",
          "countryCode": "KHM"
        },
        {
          "countryName": "韩国",
          "countryEnName": "Korea (the Republic of)",
          "countryCode": "KOR"
        },
        {
          "countryName": "科威特",
          "countryEnName": "Kuwait",
          "countryCode": "KWT"
        }
      ]
    },
    {
      "index": "L",
      "data": [
        {
          "countryName": "老挝",
          "countryEnName": "Lao People's Democratic Republic ",
          "countryCode": "LAO"
        },
        {
          "countryName": "黎巴嫩",
          "countryEnName": "Lebanon",
          "countryCode": "LBN"
        },
        {
          "countryName": "利比里亚",
          "countryEnName": "Liberia",
          "countryCode": "LBR"
        },
        {
          "countryName": "利比亚",
          "countryEnName": "Libyan Arab Jamahiriya ",
          "countryCode": "LBY"
        },
        {
          "countryName": "列支敦士登",
          "countryEnName": "Liechtenstein",
          "countryCode": "LIE"
        },
        {
          "countryName": "斯里兰卡",
          "countryEnName": "Sri Lanka",
          "countryCode": "LKA"
        },
        {
          "countryName": "立陶宛",
          "countryEnName": "Lithuania",
          "countryCode": "LTU"
        },
        {
          "countryName": "卢森堡",
          "countryEnName": "Luxembourg",
          "countryCode": "LUX"
        },
        {
          "countryName": "拉脱维亚",
          "countryEnName": "Latvia",
          "countryCode": "LVA"
        }
      ]
    },
    {
      "index": "M",
      "data": [
        {
          "countryName": "中国澳门",
          "countryEnName": "Macao",
          "countryCode": "MAC"
        },
        {
          "countryName": "摩洛哥",
          "countryEnName": "Morocco",
          "countryCode": "MAR"
        },
        {
          "countryName": "摩纳哥",
          "countryEnName": "Monaco",
          "countryCode": "MCO"
        },
        {
          "countryName": "摩尔多瓦",
          "countryEnName": "Moldova ",
          "countryCode": "MDA"
        },
        {
          "countryName": "马达加斯加",
          "countryEnName": "Madagascar",
          "countryCode": "MDG"
        },
        {
          "countryName": "马尔代夫",
          "countryEnName": "Maldives",
          "countryCode": "MDV"
        },
        {
          "countryName": "墨西哥",
          "countryEnName": "Mexico",
          "countryCode": "MEX"
        },
        {
          "countryName": "马里",
          "countryEnName": "Mali",
          "countryCode": "MLI"
        },
        {
          "countryName": "马耳他",
          "countryEnName": "Malta",
          "countryCode": "MLT"
        },
        {
          "countryName": "缅甸",
          "countryEnName": "Myanmar",
          "countryCode": "MMR"
        },
        {
          "countryName": "黑山",
          "countryEnName": "Montenegro",
          "countryCode": "MNE"
        },
        {
          "countryName": "蒙古",
          "countryEnName": "Mongolia",
          "countryCode": "MNG"
        },
        {
          "countryName": "莫桑比克",
          "countryEnName": "Mozambique",
          "countryCode": "MOZ"
        },
        {
          "countryName": "毛利塔尼亚",
          "countryEnName": "Mauritania",
          "countryCode": "MRT"
        },
        {
          "countryName": "毛里求斯",
          "countryEnName": "Mauritius",
          "countryCode": "MUS"
        },
        {
          "countryName": "马来西亚",
          "countryEnName": "Malaysia",
          "countryCode": "MYS"
        }
      ]
    },
    {
      "index": "N",
      "data": [
        {
          "countryName": "纳米比亚",
          "countryEnName": "Namibia",
          "countryCode": "NAM"
        },
        {
          "countryName": "尼日尔",
          "countryEnName": "Niger ",
          "countryCode": "NER"
        },
        {
          "countryName": "尼日利亚",
          "countryEnName": "Nigeria",
          "countryCode": "NGA"
        },
        {
          "countryName": "尼加拉瓜",
          "countryEnName": "Nicaragua",
          "countryCode": "NIC"
        },
        {
          "countryName": "荷兰",
          "countryEnName": "Netherlands ",
          "countryCode": "NLD"
        },
        {
          "countryName": "挪威",
          "countryEnName": "Norway",
          "countryCode": "NOR"
        },
        {
          "countryName": "尼泊尔",
          "countryEnName": "Nepal",
          "countryCode": "NPL"
        },
        {
          "countryName": "瑙鲁",
          "countryEnName": "Nauru",
          "countryCode": "NRU"
        },
        {
          "countryName": "新西兰",
          "countryEnName": "New Zealand",
          "countryCode": "NZL"
        }
      ]
    },
    {
      "index": "O",
      "data": [
        {
          "countryName": "阿曼",
          "countryEnName": "Oman",
          "countryCode": "OMN"
        }
      ]
    },
    {
      "index": "P",
      "data": [
        {
          "countryName": "巴基斯坦",
          "countryEnName": "Pakistan",
          "countryCode": "PAK"
        },
        {
          "countryName": "巴拿马",
          "countryEnName": "Panama",
          "countryCode": "PAN"
        },
        {
          "countryName": "秘鲁",
          "countryEnName": "Peru",
          "countryCode": "PER"
        },
        {
          "countryName": "菲律宾",
          "countryEnName": "Philippines ",
          "countryCode": "PHL"
        },
        {
          "countryName": "巴布亚新几内亚",
          "countryEnName": "Papua New Guinea",
          "countryCode": "PNG"
        },
        {
          "countryName": "波兰",
          "countryEnName": "Poland",
          "countryCode": "POL"
        },
        {
          "countryName": "波多黎各",
          "countryEnName": "Puerto Rico",
          "countryCode": "PRI"
        },
        {
          "countryName": "朝鲜",
          "countryEnName": "Korea (the Democratic People's Republic of)",
          "countryCode": "PRK"
        },
        {
          "countryName": "葡萄牙",
          "countryEnName": "Portugal",
          "countryCode": "PRT"
        },
        {
          "countryName": "巴拉圭",
          "countryEnName": "Paraguay",
          "countryCode": "PRY"
        },
        {
          "countryName": "巴勒斯坦",
          "countryEnName": "Palestinian Territory ",
          "countryCode": "PSE"
        }
      ]
    },
    {
      "index": "Q",
      "data": [
        {
          "countryName": "卡塔尔",
          "countryEnName": "Qatar",
          "countryCode": "QAT"
        }
      ]
    },
    {
      "index": "R",
      "data": [
        {
          "countryName": "罗马尼亚",
          "countryEnName": "Romania",
          "countryCode": "ROU"
        },
        {
          "countryName": "俄罗斯联邦",
          "countryEnName": "Russian Federation ",
          "countryCode": "RUS"
        },
        {
          "countryName": "卢旺达",
          "countryEnName": "Rwanda",
          "countryCode": "RWA"
        }
      ]
    },
    {
      "index": "S",
      "data": [
        {
          "countryName": "沙特阿拉伯",
          "countryEnName": "Saudi Arabia",
          "countryCode": "SAU"
        },
        {
          "countryName": "苏丹",
          "countryEnName": "Sudan ",
          "countryCode": "SDN"
        },
        {
          "countryName": "塞内加尔",
          "countryEnName": "Senegal",
          "countryCode": "SEN"
        },
        {
          "countryName": "新加坡",
          "countryEnName": "Singapore",
          "countryCode": "SGP"
        },
        {
          "countryName": "塞拉利昂",
          "countryEnName": "Sierra Leone",
          "countryCode": "SLE"
        },
        {
          "countryName": "圣马力诺",
          "countryEnName": "San Marino",
          "countryCode": "SMR"
        },
        {
          "countryName": "索马里",
          "countryEnName": "Somalia",
          "countryCode": "SOM"
        },
        {
          "countryName": "塞尔维亚",
          "countryEnName": "Serbia",
          "countryCode": "SRB"
        },
        {
          "countryName": "斯洛伐克",
          "countryEnName": "Slovakia",
          "countryCode": "SVK"
        },
        {
          "countryName": "斯洛文尼亚",
          "countryEnName": "Slovenia",
          "countryCode": "SVN"
        },
        {
          "countryName": "瑞典",
          "countryEnName": "Sweden",
          "countryCode": "SWE"
        },
        {
          "countryName": "塞舌尔",
          "countryEnName": "Seychelles",
          "countryCode": "SYC"
        },
        {
          "countryName": "叙利亚",
          "countryEnName": "Syrian Arab Republic ",
          "countryCode": "SYR"
        }
      ]
    },
    {
      "index": "T",
      "data": [
        {
          "countryName": "乍得",
          "countryEnName": "Chad",
          "countryCode": "TCD"
        },
        {
          "countryName": "泰国",
          "countryEnName": "Thailand",
          "countryCode": "THA"
        },
        {
          "countryName": "塔吉克斯坦",
          "countryEnName": "Tajikistan",
          "countryCode": "TJK"
        },
        {
          "countryName": "土库曼斯坦",
          "countryEnName": "Turkmenistan",
          "countryCode": "TKM"
        },
        {
          "countryName": "东帝汶",
          "countryEnName": "Timor-Leste",
          "countryCode": "TLS"
        },
        {
          "countryName": "突尼斯",
          "countryEnName": "Tunisia",
          "countryCode": "TUN"
        },
        {
          "countryName": "土耳其",
          "countryEnName": "Turkey",
          "countryCode": "TUR"
        },
        {
          "countryName": "中国台湾",
          "countryEnName": "Taiwan (Province of China)",
          "countryCode": "TWN"
        },
        {
          "countryName": "坦桑尼亚",
          "countryEnName": "Tanzania,United Republic of",
          "countryCode": "TZA"
        }
      ]
    },
    {
      "index": "U",
      "data": [
        {
          "countryName": "乌干达",
          "countryEnName": "Uganda",
          "countryCode": "UGA"
        },
        {
          "countryName": "乌克兰",
          "countryEnName": "Ukraine",
          "countryCode": "UKR"
        },
        {
          "countryName": "乌拉圭",
          "countryEnName": "Uruguay",
          "countryCode": "URY"
        },
        {
          "countryName": "美国",
          "countryEnName": "United States ",
          "countryCode": "USA"
        },
        {
          "countryName": "乌兹别克斯坦",
          "countryEnName": "Uzbekistan",
          "countryCode": "UZB"
        }
      ]
    },
    {
      "index": "V",
      "data": [
        {
          "countryName": "梵蒂冈",
          "countryEnName": "Vatican City",
          "countryCode": "VAT"
        },
        {
          "countryName": "委内瑞拉",
          "countryEnName": "Venezuela",
          "countryCode": "VEN"
        },
        {
          "countryName": "越南",
          "countryEnName": "Viet Nam",
          "countryCode": "VNM"
        }
      ]
    },
    {
      "index": "W",
      "data": []
    },
    {
      "index": "X",
      "data": []
    },
    {
      "index": "Y",
      "data": [
        {
          "countryName": "也门",
          "countryEnName": "Yemen",
          "countryCode": "YEM"
        }
      ]
    },
    {
      "index": "Z",
      "data": [
        {
          "countryName": "南非",
          "countryEnName": "South Africa",
          "countryCode": "ZAF"
        },
        {
          "countryName": "赞比亚",
          "countryEnName": "Zambia",
          "countryCode": "ZMB"
        },
        {
          "countryName": "津巴布韦",
          "countryEnName": "Zimbabwe",
          "countryCode": "ZWE"
        }
      ]
    }
  ],
  "suc": true
}
